techsig/__init__.py
techsig/techsig.py
techsig-1.0.6.dist-info/LICENSE.txt
techsig-1.0.6.dist-info/METADATA
techsig-1.0.6.dist-info/WHEEL
techsig-1.0.6.dist-info/top_level.txt
techsig-1.0.6.dist-info/RECORD
