Metadata-Version: 2.1
Name: techsig
Version: 1.0.6
Summary: Technical charts with signals
Home-page: UNKNOWN
Author: Aayush Talekar Saloni Jaitly
Author-email: aayush.talekar57@nmims.edu.in
License: UNKNOWN
Platform: UNKNOWN
Classifier: Programming Language :: Python :: 3
Classifier: License :: OSI Approved :: MIT License
Classifier: Operating System :: OS Independent
Requires-Python: >=3.6
Requires-Dist: yfinance
Requires-Dist: ta
Requires-Dist: numpy
Requires-Dist: pandas
Requires-Dist: plotly
